Tigris/Calcul.py
Tigris/Calcul_Convertor.py
Tigris/Combiner.py
Tigris/Crunch.py
Tigris/Element.py
Tigris/Element_Constants.py
Tigris/Element_Cuboids.py
Tigris/Element_Matrix.py
Tigris/File.py
Tigris/Graph.py
Tigris/Graph_Element.py
Tigris/Graph_Element_Constants.py
Tigris/Graph_Element_Cuboids.py
Tigris/Graph_Element_Matrix.py
Tigris/Graph_Legend.py
Tigris/Graph_MPL.py
Tigris/Graph_Style.py
Tigris/Graph_VTK.py
Tigris/Hytec.py
Tigris/IHM_Files.py
Tigris/IHM_Parameters.py
Tigris/Min3p.py
Tigris/Page.py
Tigris/Pages_Manager.py
Tigris/Porflow.py
Tigris/Style.py
Tigris/Style_Dialog.py
Tigris/Tigris.py
Tigris/__init__.py
Tigris/utils.py
Tigris/utils_mpl.py
Tigris/utils_qt.py
Tigris/utils_vtk.py
tigris_cea-0.6.dist-info/METADATA
tigris_cea-0.6.dist-info/WHEEL
tigris_cea-0.6.dist-info/top_level.txt
tigris_cea-0.6.dist-info/RECORD
