Metadata-Version: 2.4
Name: tigris_cea
Version: 0.6
Summary: Post-treatment of Porflow, Hytec, Min3P and Crunch simulations
Home-page: https://github.com/julientrincal/Tigris
Author: Julien TRINCAL
Author-email: julien.trincal@cea.fr
License: none
Keywords: Porflow,Hytec,Min3P,Crunch
Requires-Dist: matplotlib>=3.8.4
Requires-Dist: netCDF4>=1.7.2
Requires-Dist: numpy>=2.2.5
Requires-Dist: openpyxl>=3.1.5
Requires-Dist: PyQt5>=5.15.11
Requires-Dist: requests>=2.32.3
Requires-Dist: shapely>=2.1.0
Requires-Dist: vtk>=9.4.2
Dynamic: author
Dynamic: author-email
Dynamic: home-page
Dynamic: keywords
Dynamic: license
Dynamic: requires-dist
Dynamic: summary
